[
  {
    "id": "1765266567485",
    "code": "Электронный Знак",
    "name": "Электронный Знак",
    "createdAt": "2025-12-09T07:49:27.485Z",
    "updatedAt": "2025-12-09T08:42:31.943Z"
  },
  {
    "id": "1765276266988",
    "code": "SAP_ERP",
    "name": "SE16n",
    "createdAt": "2025-12-09T10:31:06.990Z",
    "updatedAt": "2025-12-09T10:31:06.990Z"
  },
  {
    "id": "1765276393083",
    "code": "SAP_ERP",
    "name": "SAP_ERP",
    "createdAt": "2025-12-09T10:33:13.083Z",
    "updatedAt": "2025-12-09T10:33:13.083Z"
  }
]
